PygameX/__init__.py
PygameX/all_objects.py
PygameX/color.py
PygameX/exceptions.py
PygameX/game.py
PygameX/key.py
PygameX/math.py
PygameX/objects/Circle.py
PygameX/objects/Line.py
PygameX/objects/Object.py
PygameX/objects/Rect.py
PygameX/objects/Sound.py
PygameX/objects/Sprite.py
PygameX/objects/TextDisplay.py
PygameX-0.2.dist-info/LICENSE
PygameX-0.2.dist-info/METADATA
PygameX-0.2.dist-info/WHEEL
PygameX-0.2.dist-info/top_level.txt
PygameX-0.2.dist-info/RECORD
