Metadata-Version: 2.1
Name: PygameX
Version: 0.2
Summary: A library that improves pygame and makes it structured.
Author-email: k0cteJl <immortalldeveloper@gmail.com>
License: This project is licensed under the MIT License.
Classifier: Programming Language :: Python :: 3
Classifier: License :: OSI Approved :: MIT License
Classifier: Operating System :: OS Independent
Requires-Python: >=3.6
License-File: LICENSE
Requires-Dist: pygame
